pi_weatherstation/__init__.py
pi_weatherstation/cli.py
pi_weatherstation-0.0.5.dist-info/LICENSE
pi_weatherstation-0.0.5.dist-info/METADATA
pi_weatherstation-0.0.5.dist-info/WHEEL
pi_weatherstation-0.0.5.dist-info/entry_points.txt
pi_weatherstation-0.0.5.dist-info/top_level.txt
pi_weatherstation-0.0.5.dist-info/RECORD
