Metadata-Version: 2.1
Name: pi-weatherstation
Version: 0.0.5
Summary: Read the data from pimoroni BME680 and display on pimoroni SPI screen
Home-page: http://github.com/guilhermef/pi_weatherstation
Author: Guilherme Souza
Author-email: guilherme@souza.tech
License: MIT
Platform: UNKNOWN
Classifier: Development Status :: 4 - Beta
Classifier: Programming Language :: Python
Classifier: Programming Language :: Python :: 3.6
Classifier: Programming Language :: Python :: 3.7
Classifier: Programming Language :: Python :: 3.8
Classifier: Programming Language :: Python :: 3.9
Classifier: Framework :: AsyncIO
Classifier: Operating System :: POSIX :: Linux
Classifier: Topic :: Utilities
Classifier: License :: OSI Approved :: MIT License
Requires-Dist: async-imgkit (<1.0)
Requires-Dist: jinja2 (<3.0)
Requires-Dist: asyncio-periodic (==2019.2)
Requires-Dist: aioprometheus[aiohttp] (<21.0)
Requires-Dist: Pillow (<9.0)
Provides-Extra: bme680
Requires-Dist: bme680 (<2.0) ; extra == 'bme680'
Requires-Dist: smbus (==1.1.post2) ; extra == 'bme680'
Provides-Extra: st7789
Requires-Dist: st7789 (<1.0) ; extra == 'st7789'
Requires-Dist: numpy (<2.0) ; extra == 'st7789'
Requires-Dist: spidev (<4.0) ; extra == 'st7789'
Requires-Dist: RPi.GPIO (<1.0) ; extra == 'st7789'
